local_text_summarizer/__init__.py
local_text_summarizer/summarize.py
locat_text_summarizer/__init__.py
locat_text_summarizer/summarize.py
local_text_summarizer-0.2.dist-info/LICENSE
local_text_summarizer-0.2.dist-info/METADATA
local_text_summarizer-0.2.dist-info/WHEEL
local_text_summarizer-0.2.dist-info/entry_points.txt
local_text_summarizer-0.2.dist-info/top_level.txt
local_text_summarizer-0.2.dist-info/RECORD
