Metadata-Version: 2.1
Name: local_text_summarizer
Version: 0.2
Summary: A package for simple local text summarization.
Home-page: https://github.com/tunahorse/local_text_summarizer
Author: Fabian Anguiano
Author-email: fabiananguiano@gmail.com
Classifier: Programming Language :: Python :: 3
Classifier: License :: OSI Approved :: MIT License
Classifier: Operating System :: OS Independent
License-File: LICENSE
Requires-Dist: nltk
